local_cname/__init__.py
local_cname/__main__.py
local_cname/cli.py
local_cname-0.3.dist-info/DESCRIPTION.rst
local_cname-0.3.dist-info/METADATA
local_cname-0.3.dist-info/RECORD
local_cname-0.3.dist-info/WHEEL
local_cname-0.3.dist-info/entry_points.txt
local_cname-0.3.dist-info/metadata.json
local_cname-0.3.dist-info/top_level.txt
