Metadata-Version: 2.0
Name: local-cname
Version: 0.3
Summary: Helper script to emulate a local CNAME DNS by writing to /etc/hosts
Home-page: https://github.com/hjacobs/local-cname
Author: henning@jacobs1.de
Author-email: UNKNOWN
License: GNU General Public License v3 (GPLv3)
Keywords: dns hosts local
Platform: UNKNOWN
Classifier: Programming Language :: Python
Classifier: Programming Language :: Python :: 3.4
Classifier: Programming Language :: Python :: 3.5
Classifier: Programming Language :: Python :: 3.6
Classifier: Intended Audience :: Developers
Classifier: Development Status :: 3 - Alpha
Classifier: Operating System :: POSIX
Requires-Dist: clickclick
